AksharaJaana/__init__.py
AksharaJaana/main.py
AksharaJaana/utils.py
AksharaJaana-1.0.1.3.dist-info/METADATA
AksharaJaana-1.0.1.3.dist-info/WHEEL
AksharaJaana-1.0.1.3.dist-info/top_level.txt
AksharaJaana-1.0.1.3.dist-info/RECORD
