Metadata-Version: 2.1
Name: AksharaJaana
Version: 1.0.1.3
Summary: A Kannada OCR
Home-page: https://github.com/Navaneeth-Sharma/Akshara-Jaana/
Author: Navaneeth
Author-email: navaneethsharma2310oct@gmail.com
Classifier: Programming Language :: Python :: 3
Classifier: License :: OSI Approved :: MIT License
Classifier: Operating System :: OS Independent
Requires-Python: >=3.6
